sdab/__init__.py
sdab-0.1.2.dist-info/LICENSE
sdab-0.1.2.dist-info/METADATA
sdab-0.1.2.dist-info/WHEEL
sdab-0.1.2.dist-info/top_level.txt
sdab-0.1.2.dist-info/RECORD
