Metadata-Version: 2.1
Name: sdab
Version: 0.1.2
Summary: Khmer Speech To Text Inference API using Wav2Vec2 with Pretrain Model
Home-page: https://github.com/MetythornPenn/sdab.git
Author: Metythorn Penn
Author-email: metythorn@gmail.com
License: Apache Software License 2.0
Keywords: asr
Platform: UNKNOWN
Classifier: Natural Language :: English
Classifier: License :: OSI Approved :: Apache Software License
Classifier: Operating System :: OS Independent
Classifier: Programming Language :: Python :: 3
Requires-Dist: datasets
Requires-Dist: transformers
Requires-Dist: torchaudio
Requires-Dist: soundfile
Requires-Dist: torch
Requires-Dist: numpy
